{
  "todos": [
    {
      "id": "rwachpb",
      "todo": "1111",
      "status": true,
      "category": "monday"
    },
    {
      "id": "0r8izxa",
      "todo": "2222",
      "status": true,
      "category": "tuesday"
    },
    {
      "id": "oiv7kew",
      "todo": "3333",
      "status": false,
      "category": "wednesday"
    },
    {
      "id": "79y72z4",
      "todo": "44444",
      "status": true,
      "category": "thursday"
    },
    {
      "id": "3gutkob",
      "todo": "55555",
      "status": false,
      "category": "friday"
    },
    {
      "id": "rpxgaah",
      "todo": "aaaaa",
      "status": false,
      "category": "monday"
    },
    {
      "id": "6rae1kz",
      "todo": "bbbbb",
      "status": false,
      "category": "tuesday"
    }
  ]
}